<team>
    <member>
        <id>8978</id>
        <name>Afraa</name>
        <email>bbbb@hkhk.com</email>
        <major>Cs</major>
    </member>
    <member>
        <id>7857</id>
        <name>Arwa</name>
        <email>bbbb@hkhk.com</email>
        <major>Cs</major>
    </member>
    <member>
        <id>1234</id>
        <name>Faisal</name>
        <email>aaaa@hkhk.com</email>
        <major>Cs</major>
    </member>
    <member>
        <id>8978</id>
        <name>Abdulrahman</name>
        <email>bbbb@hkhk.com</email>
        <major>Cs</major>
    </member>
     <member>
        <id>8978</id>
        <name>Turki</name>
        <email>bbbb@hkhk.com</email>
        <major>Cs</major>
    </member>
    
</team>